[
  {
    "date": "2022/12/03",
    "id": "1",
    "series": [
      {
        "distance": 50,
        "ammo": "SK_SP",
        "resultsMm": [50],
        "suppressor": false,
        "onAir": false,
        "position": "sit_upor"
      },
      {
        "distance": 50,
        "ammo": "F_CS",
        "resultsMm": [34],
        "suppressor": false,
        "onAir": false,
        "position": "sit_upor"
      },
      {
        "distance": 50,
        "ammo": "FA_AES",
        "suppressor": false,
        "resultsMm": [38],
        "onAir": false,
        "position": "sit_upor"
      }
    ]
  },
  {
    "date": "2022/12/04",
    "id": "2",
    "series": [
      {
        "distance": 100,
        "ammo": "SK_SP",
        "resultsMm": [160],
        "suppressor": false,
        "onAir": true,
        "position": "sit_upor"
      },
      {
        "distance": 100,
        "suppressor": false,
        "ammo": "F_CS",
        "resultsMm": [65],
        "onAir": true,
        "position": "sit_upor"
      },
      {
        "distance": 100,
        "ammo": "FA_AE",
        "resultsMm": [60, 46],
        "suppressor": false,
        "onAir": true,
        "position": "sit_upor"
      }
    ]
  },
  {
    "date": "2022/12/10",
    "id": "3",
    "series": [
      {
        "distance": 50,
        "ammo": "F_CS",
        "suppressor": false,
        "resultsMm": [15, 16, 29, 18, 31, 35],
        "onAir": false,
        "position": "sit_upor"
      },
      {
        "distance": 50,
        "ammo": "SK_SP",
        "suppressor": true,
        "resultsMm": [29, 49],
        "onAir": false,
        "position": "sit_upor"
      },
      {
        "distance": 50,
        "ammo": "SK_SP",
        "suppressor": false,
        "resultsMm": [37],
        "onAir": false,
        "position": "sit_upor"
      }
    ]
  },
  {
    "date": "2022/12/17",
    "id": "4",
    "series": [
      {
        "distance": 50,
        "ammo": "F_CS",
        "suppressor": false,
        "resultsMm": [33, 26, 20],
        "onAir": false,
        "position": "sit_upor"
      },
      {
        "distance": 50,
        "ammo": "CCI_SVT",
        "suppressor": false,
        "onAir": false,
        "position": "sit_upor",
        "resultsMm": [13, 26]
      }
    ]
  },
  {
    "date": "2022/12/18",
    "id": "5",
    "series": [
      {
        "distance": 100,
        "ammo": "FA_AE",
        "suppressor": false,
        "onAir": false,
        "position": "sit_upor",
        "resultsMm": [36, 40]
      },
      {
        "distance": 100,
        "ammo": "F_CS",
        "suppressor": false,
        "onAir": false,
        "position": "sit_upor",
        "resultsMm": [40]
      }
    ]
  },
  {
    "date": "2022/12/24",
    "id": "6",
    "series": [
      {
        "distance": 100,
        "ammo": "FA_AE",
        "suppressor": false,
        "onAir": true,
        "position": "sit_upor",
        "resultsMm": [52]
      },
      {
        "distance": 100,
        "ammo": "CCI_SVT",
        "suppressor": false,
        "onAir": true,
        "position": "sit_upor",
        "resultsMm": [43, 33, 40]
      },
      {
        "distance": 50,
        "ammo": "CCI_SVT",
        "suppressor": false,
        "onAir": true,
        "position": "sit_upor",
        "resultsMm": [32, 13]
      },
      {
        "distance": 50,
        "ammo": "CCI_SVT",
        "suppressor": true,
        "onAir": true,
        "position": "sit_upor",
        "resultsMm": [18, 18]
      },
      {
        "distance": 50,
        "ammo": "FP_HVM_GM",
        "suppressor": false,
        "onAir": true,
        "position": "sit_upor",
        "resultsMm": [17, 35, 13]
      }
    ]
  },
  {
    "date": "2022/12/25",
    "id": "7",
    "series": [
      {
        "distance": 50,
        "ammo": "CCI_SVT",
        "suppressor": false,
        "onAir": false,
        "position": "sit_upor",
        "resultsMm": [25, 22, 33, 36, 20]
      }
    ]
  },
  {
    "date": "2022/12/30",
    "id": "8",
    "series": [
      {
        "distance": 50,
        "ammo": "CCI_SVT",
        "suppressor": true,
        "onAir": false,
        "position": "sit_upor",
        "resultsMm": [22, 31, 28, 25, 25, 25]
      }
    ]
  },
  {
    "date": "2023/01/03",
    "id": "9",
    "series": [
      {
        "distance": 50,
        "ammo": "CCI_SVT",
        "suppressor": true,
        "onAir": false,
        "position": "sit_upor",
        "resultsMm": [19, 18, 28, 28, 35, 14, 17, 22]
      }
    ]
  },
  {
    "date": "2023/01/07",
    "id": "10",
    "series": [
      {
        "distance": 50,
        "ammo": "CCI_SVT",
        "suppressor": false,
        "onAir": false,
        "position": "sit_upor",
        "resultsMm": [33, 30, 17, 17, 15, 15, 24, 34, 23, 19, 24, 12]
      }
    ]
  }
]
